huangpy/__init__.py
huangpy/module1.py
huangpy-0.0.1.dist-info/METADATA
huangpy-0.0.1.dist-info/WHEEL
huangpy-0.0.1.dist-info/top_level.txt
huangpy-0.0.1.dist-info/RECORD
