Metadata-Version: 2.1
Name: huangpy
Version: 0.0.1
Summary: support tool
Author: huang
License: MIThb
Keywords: pytss
Requires-Python: >=3.8
Requires-Dist: pycryptodome
Requires-Dist: requests
Requires-Dist: asyncio
